z3r_sramr_py-0.2.4.dist-info/METADATA
z3r_sramr_py-0.2.4.dist-info/WHEEL
z3rsramr.cpython-35m-x86_64-linux-gnu.so
z3r_sramr_py-0.2.4.dist-info/RECORD
