Metadata-Version: 2.1
Name: z3r-sramr-py
Version: 0.2.4
Classifier: Programming Language :: Python
Classifier: Programming Language :: Python :: 3.6
Classifier: Programming Language :: Python :: 3.7
Classifier: Programming Language :: Python :: 3.8
Classifier: Programming Language :: Rust
Classifier: Operating System :: POSIX :: Linux
Classifier: Operating System :: Microsoft :: Windows
Classifier: Operating System :: MacOS :: MacOS X
Classifier: License :: OSI Approved :: MIT License
Keywords: zelda randomizer sram alttp snes
Author: cassidoxa <cassidymoen@gmx.com>
Author-Email: cassidoxa <cassidymoen@gmx.com>
License: MIT
